setup.py
metafolder/__init__.py
metafolder/folder.py
metafolder.egg-info/PKG-INFO
metafolder.egg-info/SOURCES.txt
metafolder.egg-info/dependency_links.txt
metafolder.egg-info/namespace_packages.txt
metafolder.egg-info/not-zip-safe
metafolder.egg-info/requires.txt
metafolder.egg-info/top_level.txt