Metadata-Version: 1.1
Name: metafolder
Version: 0.1.2
Summary: Store a bunch of documents alongside basic metadata
Home-page: http://pudo.org
Author: Friedrich Lindenberg
Author-email: friedrich@pudo.org
License: MIT
Platform: UNKNOWN
Classifier: Development Status :: 3 - Alpha
Classifier: Intended Audience :: Developers
Classifier: Operating System :: OS Independent
Classifier: Programming Language :: Python
